viz_mcp/__init__.py
viz_mcp/auto_detect.py
viz_mcp/chart_generator.py
viz_mcp/insights_generator.py
viz_mcp/viz_server.py
viz_mcp-1.0.1.dist-info/licenses/LICENSE
viz_mcp-1.0.1.dist-info/METADATA
viz_mcp-1.0.1.dist-info/WHEEL
viz_mcp-1.0.1.dist-info/entry_points.txt
viz_mcp-1.0.1.dist-info/top_level.txt
viz_mcp-1.0.1.dist-info/RECORD
