Metadata-Version: 2.4
Name: viz-mcp
Version: 1.0.1
Summary: MCP server for data visualization from tracking-mcp
Requires-Python: >=3.10
License-File: LICENSE
Requires-Dist: mcp>=1.7.1
Requires-Dist: matplotlib>=3.8.0
Requires-Dist: plotly>=5.18.0
Requires-Dist: pandas>=2.1.0
Requires-Dist: numpy>=1.26.0
Requires-Dist: seaborn>=0.13.0
Requires-Dist: kaleido>=0.2.1
Provides-Extra: dev
Requires-Dist: pytest>=7.4.0; extra == "dev"
Requires-Dist: pytest-asyncio>=0.21.0; extra == "dev"
Dynamic: license-file
